best/__init__.py
best/integration/__init__.py
best/unit/__init__.py
best/unit/conftest.py
best/unit/test_glue_session.py
best/unit/test_glue_session_demo.py
best/unit/test_session_apis.py
hyperpod_nemo_adapter-100.0.0.dist-info/LICENSE.txt
hyperpod_nemo_adapter-100.0.0.dist-info/METADATA
hyperpod_nemo_adapter-100.0.0.dist-info/WHEEL
hyperpod_nemo_adapter-100.0.0.dist-info/top_level.txt
hyperpod_nemo_adapter-100.0.0.dist-info/RECORD
